__init__.py
keycloak_utils/__init__.py
keycloak_utils/errors.py
keycloak_utils/utils.py
keycloak_utils/authentication/__init__.py
keycloak_utils/authentication/fastapi.py
keycloak_utils/authentication/rest_framework.py
keycloak_utils/backend/__init__.py
keycloak_utils/backend/base.py
keycloak_utils/backend/fastapi.py
keycloak_utils/backend/rest_framework.py
keycloak_utils/consumer/__init__.py
keycloak_utils/consumer/core.py
keycloak_utils/consumer/django/__init__.py
keycloak_utils/consumer/django/strategies.py
keycloak_utils/contrib/__init__.py
keycloak_utils/contrib/django/__init__.py
keycloak_utils/contrib/django/apps.py
keycloak_utils/contrib/django/auth.py
keycloak_utils/contrib/django/conf.py
keycloak_utils/contrib/django/urls.py
keycloak_utils/contrib/django/views.py
keycloak_utils/contrib/django/management/__init__.py
keycloak_utils/contrib/django/management/commands/__init__.py
keycloak_utils/contrib/django/management/commands/run_consumer.py
keycloak_utils/contrib/django/management/commands/sync_keycloak.py
keycloak_utils/manager/__init__.py
keycloak_utils/manager/base.py
keycloak_utils/manager/fastapi.py
keycloak_utils/manager/rest_framework.py
keycloak_utils/sync/__init__.py
keycloak_utils/sync/kc_admin.py
keycloak_utils/sync/static.py
keycloak_utils/sync/tasks.py
keycloak_utils/sync/django/__init__.py
keycloak_utils/sync/django/core.py
keycloak_utils/verifier/__init__.py
keycloak_utils/verifier/base.py
keycloak_utils/verifier/fastapi.py
keycloak_utils/verifier/rest_framework.py
keycloak_utils-0.12.2.dist-info/METADATA
keycloak_utils-0.12.2.dist-info/WHEEL
keycloak_utils-0.12.2.dist-info/top_level.txt
keycloak_utils-0.12.2.dist-info/RECORD
