Metadata-Version: 2.4
Name: keycloak-utils
Version: 0.12.2
Summary: Helper classes for keycloak authentication in Django and FastAPI
Author-email: Jerin Peter George <jerinpetergeorge@gmail.com>
Project-URL: Homepage, https://github.com/ottuco/keycloak-auth-utils.git
Classifier: Environment :: Web Environment
Classifier: Environment :: Console
Classifier: Intended Audience :: Developers
Classifier: Operating System :: OS Independent
Classifier: Programming Language :: Python
Classifier: Programming Language :: Python :: 3.7
Classifier: Programming Language :: Python :: 3.8
Classifier: Programming Language :: Python :: 3.9
Classifier: Programming Language :: Python :: 3.10
Classifier: Programming Language :: Python :: 3.11
Classifier: Topic :: Utilities
Requires-Python: >=3.7
Requires-Dist: requests>=2.31.0
Requires-Dist: pyjwt[crypto]>=2.8.0
Requires-Dist: python-keycloak>=4.6.2
Requires-Dist: pika>=1.3.2
Requires-Dist: msgpack>=1.0.0
Requires-Dist: pydantic>=1.10.12
Requires-Dist: httpx>=0.24.0
Requires-Dist: asgiref>=3.6.0
Provides-Extra: django
Requires-Dist: djangorestframework>=3.12.0; extra == "django"
Requires-Dist: Django>=3.2; extra == "django"
Requires-Dist: redis>=5.0.3; extra == "django"
Requires-Dist: django-tenants>=3.7.0; extra == "django"
Provides-Extra: fastapi
Requires-Dist: fastapi>=0.68.0; extra == "fastapi"
Provides-Extra: django-sync
Requires-Dist: keycloak-utils[django]; extra == "django-sync"
Requires-Dist: celery>=5.4.0; extra == "django-sync"
Provides-Extra: all
Requires-Dist: keycloak-utils[django-sync,fastapi]; extra == "all"
Provides-Extra: tox
Requires-Dist: tox>=4.0.0; extra == "tox"
Provides-Extra: pytest
Requires-Dist: pytest>=7.0.0; extra == "pytest"
Provides-Extra: test-fastapi
Requires-Dist: keycloak-utils[fastapi,pytest,tox]; extra == "test-fastapi"
Provides-Extra: test-django
Requires-Dist: keycloak-utils[django-sync,pytest,tox]; extra == "test-django"
Requires-Dist: pytest-django>=4.5.2; extra == "test-django"
Provides-Extra: lint-and-formatting
Requires-Dist: black; extra == "lint-and-formatting"
Requires-Dist: flake8; extra == "lint-and-formatting"
Requires-Dist: flake8-print; extra == "lint-and-formatting"
Requires-Dist: isort; extra == "lint-and-formatting"
Requires-Dist: pre-commit; extra == "lint-and-formatting"
Provides-Extra: dev
Requires-Dist: keycloak-utils[lint-and-formatting,test]; extra == "dev"
Requires-Dist: bump2version~=1.0.1; extra == "dev"
